sequence_detector.v
module sequence_detector_1001(
    input clk,
    input in,
    input reset,
    output reg out
);
reg [1:0] state;
parameter a= 2'b00,
          b= 2'b01,
          c= 2'b10,
          d=2'b11;
always @(posedge clk or posedge reset) begin
    if (reset)
    begin
    state <= a;
    out <= 1'b0;
    end
    else
    begin
        case(state)
        a:
        begin
            if (in)
            state <=b;
            else
            state <= a;
            out <= 1'b0;
        end
        b:
        begin
            if(in)
            state <= b;
            else
            state <= c;
            out <= 1'b0;
        end
        c:
        begin
            if(in)
            state <= b; 
            else
            state <= d;
            out <= 1'b0;
        end
        d:
        begin
            if(in)
            begin
                state<= b;
                out <= 1'b1;
            end
            else
            begin 
                state<= a;
                out <= 1'b0;
            end
        end
        endcase
    end
end
endmodule

tb_sequence_detector_1001.v
`timescale 1ns/1ps

module tb_sequence_detector_1001;

    reg clk;
    reg in;
    reg reset;
    wire out;

    sequence_detector_1001 uut (
        .clk(clk),
        .in(in),
        .reset(reset),
        .out(out)
    );

    
    always #5 clk = ~clk;

    
    reg [10:0] input_sequence = 11'b10010011001;
    integer i;

    initial begin
       
        $dumpfile("dump.vcd");
        $dumpvars(0, tb_sequence_detector_1001);

        
        clk = 0;
        reset = 1;
        in = 0;

        #10;
        reset = 0;

        
        for (i = 0; i < 11; i = i + 1) begin
            in = input_sequence[i];
            #10;
        end

        #20;
        $finish;
    end

    
    initial begin
        $display("Time\tclk\tin\treset\tout");
        $monitor("%0dns\t%b\t%b\t%b\t%b", $time, clk, in, reset, out);
    end

endmodule

dump.vcd
$date
	Sat Jul 12 17:29:00 2025
$end
$version
	Icarus Verilog
$end
$timescale
	1ps
$end
$scope module tb_sequence_detector_1001 $end
$var wire 1 ! out $end
$var reg 1 " clk $end
$var reg 1 # in $end
$var reg 11 $ input_sequence [10:0] $end
$var reg 1 % reset $end
$var integer 32 & i [31:0] $end
$scope module uut $end
$var wire 1 " clk $end
$var wire 1 # in $end
$var wire 1 % reset $end
$var parameter 2 ' a $end
$var parameter 2 ( b $end
$var parameter 2 ) c $end
$var parameter 2 * d $end
$var reg 1 ! out $end
$var reg 2 + state [1:0] $end
$upscope $end
$upscope $end
$enddefinitions $end
$comment Show the parameter values. $end
$dumpall
b11 *
b10 )
b1 (
b0 '
$end
#0
$dumpvars
b0 +
bx &
1%
b10010011001 $
0#
0"
0!
$end
#5000
1"
#10000
0"
1#
b0 &
0%
#15000
b1 +
1"
#20000
0"
0#
b1 &
#25000
b10 +
1"
#30000
0"
b10 &
#35000
b11 +
1"
#40000
0"
1#
b11 &
#45000
1!
b1 +
1"
#50000
0"
b100 &
#55000
0!
1"
#60000
0"
0#
b101 &
#65000
b10 +
1"
#70000
0"
b110 &
#75000
b11 +
1"
#80000
0"
1#
b111 &
#85000
1!
b1 +
1"
#90000
0"
0#
b1000 &
#95000
0!
b10 +
1"
#100000
0"
b1001 &
#105000
b11 +
1"
#110000
0"
1#
b1010 &
#115000
1!
b1 +
1"
#120000
0"
b1011 &
#125000
0!
1"
